{"success": true, "message": "", "result": [{"Id": 48002113, "TimeStamp": "2020-01-05T02:35:00.37", "Quantity": 20558.47, "Price": 0.00132, "Total": 27.1371804, "FillType": "FILL", "OrderType": "BUY", "Uuid": "c250b57b-4952-4bae-8c0a-01c93590d2d3"}, {"Id": 47989553, "TimeStamp": "2020-01-04T18:57:21.08", "Quantity": 15180.0, "Price": 0.00133, "Total": 20.1894, "FillType": "FILL", "OrderType": "SELL", "Uuid": "2f08f875-9017-46b5-99e1-7465296cc193"}, {"Id": 47969251, "TimeStamp": "2020-01-04T08:05:41.8", "Quantity": 60.0, "Price": 0.00135, "Total": 0.081, "FillType": "FILL", "OrderType": "SELL", "Uuid": "bec0461d-3c3b-4d36-81ce-5e200674e1c9"}, {"Id": 47969248, "TimeStamp": "2020-01-04T08:05:41.77", "Quantity": 39940.0, "Price": 0.00135, "Total": 53.919, "FillType": "FILL", "OrderType": "SELL", "Uuid": "cde031bc-7629-429b-bc65-3e58c99e88fd"}, {"Id": 47952944, "TimeStamp": "2020-01-03T22:40:24.56", "Quantity": 5967.29920038, "Price": 0.00128, "Total": 7.6381429764864, "FillType": "FILL", "OrderType": "SELL", "Uuid": "21953d84-4bec-4d34-96e6-d1441599c052"}, {"Id": 47950124, "TimeStamp": "2020-01-03T21:25:13.62", "Quantity": 10000.0, "Price": 0.00127, "Total": 12.7, "FillType": "FILL", "OrderType": "SELL", "Uuid": "4f77f511-7822-4cd3-8bc4-2f2b9eafe3ed"}, {"Id": 47242555, "TimeStamp": "2020-01-03T14:53:57.61", "Quantity": 2074.46472192, "Price": 0.00125, "Total": 2.5930809024, "FillType": "FILL", "OrderType": "SELL", "Uuid": "4d2ce5b5-69a3-4360-b276-5fed98755723"}, {"Id": 47242335, "TimeStamp": "2020-01-03T14:45:38.25", "Quantity": 8374.20982933, "Price": 0.00132, "Total": 11.0539569747156, "FillType": "FILL", "OrderType": "SELL", "Uuid": "7d875e30-4bb8-42a7-94a8-ed0ce978786f"}, {"Id": 47242334, "TimeStamp": "2020-01-03T14:45:38.23", "Quantity": 7709.38888888, "Price": 0.00132, "Total": 10.1763933333216, "FillType": "FILL", "OrderType": "SELL", "Uuid": "c0b35c67-4103-4c95-992b-731a75426bf5"}, {"Id": 47242331, "TimeStamp": "2020-01-03T14:45:37.8", "Quantity": 7837.23700333, "Price": 0.00132, "Total": 10.3451528443956, "FillType": "FILL", "OrderType": "BUY", "Uuid": "3d7a6677-55a5-4b1b-8bd6-fd4fdd67993c"}, {"Id": 47242330, "TimeStamp": "2020-01-03T14:45:37.8", "Quantity": 1400.14213684, "Price": 0.00132, "Total": 1.8481876206288, "FillType": "FILL", "OrderType": "BUY", "Uuid": "8119b3ae-4057-440a-a6b2-03b81335f287"}, {"Id": 47237151, "TimeStamp": "2020-01-03T12:59:12.34", "Quantity": 3083.81183047, "Price": 0.00129, "Total": 3.9781172613063, "FillType": "FILL", "OrderType": "SELL", "Uuid": "2ccbf21a-aaaf-4588-b65b-ae96fdb217fe"}, {"Id": 47237033, "TimeStamp": "2020-01-03T12:54:34.7", "Quantity": 1916.18816953, "Price": 0.0013, "Total": 2.491044620389, "FillType": "FILL", "OrderType": "BUY", "Uuid": "f030bb76-c212-4a0e-af36-c817358c9072"}, {"Id": 47234465, "TimeStamp": "2020-01-03T11:52:50.25", "Quantity": 3758.94444444, "Price": 0.00131, "Total": 4.9242172222164, "FillType": "FILL", "OrderType": "BUY", "Uuid": "5b9585c0-2188-40f6-8a5b-9b622d2d8353"}, {"Id": 47228836, "TimeStamp": "2020-01-03T09:32:04.78", "Quantity": 9000.0, "Price": 0.0013, "Total": 11.7, "FillType": "FILL", "OrderType": "BUY", "Uuid": "4039784e-aeaa-4544-9c1c-2c5c075e1cf2"}, {"Id": 47221619, "TimeStamp": "2020-01-03T06:34:28.43", "Quantity": 4485.04809606, "Price": 0.00129, "Total": 5.7857120439174, "FillType": "FILL", "OrderType": "BUY", "Uuid": "c2c06a5f-671e-42c2-97bc-db306b8dcb42"}, {"Id": 47221600, "TimeStamp": "2020-01-03T06:34:08.28", "Quantity": 22800.64541256, "Price": 0.00129, "Total": 29.4128325822024, "FillType": "FILL", "OrderType": "BUY", "Uuid": "4e63dd48-04cb-499c-84b7-b68d9cf9d44a"}, {"Id": 47221598, "TimeStamp": "2020-01-03T06:34:08.09", "Quantity": 8572.58109386, "Price": 0.00129, "Total": 11.0586296110794, "FillType": "FILL", "OrderType": "BUY", "Uuid": "e48a8372-5e53-4d50-ae8e-2b59e9fcd3c7"}, {"Id": 47219982, "TimeStamp": "2020-01-03T05:45:42.85", "Quantity": 12454.5, "Price": 0.00128, "Total": 15.94176, "FillType": "FILL", "OrderType": "SELL", "Uuid": "c5eefecd-4d46-4381-83fa-392f888037fa"}, {"Id": 47190577, "TimeStamp": "2020-01-02T17:14:49.36", "Quantity": 52713.60273109, "Price": 0.00119, "Total": 62.7291872499971, "FillType": "FILL", "OrderType": "BUY", "Uuid": "7c26dfa7-ee6a-4516-ac02-4bd2e9b05b84"}, {"Id": 47190576, "TimeStamp": "2020-01-02T17:14:49.35", "Quantity": 248634.0122689, "Price": 0.00119, "Total": 295.874474599991, "FillType": "FILL", "OrderType": "BUY", "Uuid": "38f54f14-a318-482d-8023-c333886fec2b"}, {"Id": 47190570, "TimeStamp": "2020-01-02T17:14:47.77", "Quantity": 7000.0, "Price": 0.00125, "Total": 8.75, "FillType": "FILL", "OrderType": "SELL", "Uuid": "76698e6e-bceb-4f80-8812-4cc06c18ef16"}, {"Id": 47190569, "TimeStamp": "2020-01-02T17:14:47.77", "Quantity": 8064.51612903, "Price": 0.00124, "Total": 9.9999999999972, "FillType": "FILL", "OrderType": "SELL", "Uuid": "c1fd7724-9cd6-4eb6-9f49-f56077e2fe0c"}, {"Id": 47190568, "TimeStamp": "2020-01-02T17:14:47.77", "Quantity": 1500.0, "Price": 0.0012, "Total": 1.8, "FillType": "FILL", "OrderType": "SELL", "Uuid": "6cd23444-b417-499b-b786-d042307d6565"}, {"Id": 47190567, "TimeStamp": "2020-01-02T17:14:47.77", "Quantity": 11336.70398209, "Price": 0.00111, "Total": 12.5837414201199, "FillType": "FILL", "OrderType": "SELL", "Uuid": "6347ea3d-5cdb-4670-a231-42ed38b01890"}, {"Id": 47190566, "TimeStamp": "2020-01-02T17:14:47.77", "Quantity": 677.07027776, "Price": 0.00126, "Total": 0.8531085499776, "FillType": "FILL", "OrderType": "SELL", "Uuid": "909267a3-2470-46bb-91fc-1cc5d2430be4"}, {"Id": 47189381, "TimeStamp": "2020-01-02T17:04:31.38", "Quantity": 21891.85, "Price": 0.00126, "Total": 27.583731, "FillType": "FILL", "OrderType": "SELL", "Uuid": "ce7c70aa-c7d3-40ad-a9da-389a1fd837b0"}, {"Id": 47185476, "TimeStamp": "2020-01-02T16:35:49.8", "Quantity": 20622.47659875, "Price": 0.00127, "Total": 26.1905452804125, "FillType": "FILL", "OrderType": "SELL", "Uuid": "04493a16-8a2a-4ca7-a913-880965ea7c62"}, {"Id": 47185475, "TimeStamp": "2020-01-02T16:35:49.8", "Quantity": 20796.66838266, "Price": 0.00127, "Total": 26.4117688459782, "FillType": "FILL", "OrderType": "SELL", "Uuid": "3c2ff419-2531-4b68-9993-7589826a5de1"}, {"Id": 47174099, "TimeStamp": "2020-01-02T09:25:15.24", "Quantity": 5193.12952393, "Price": 0.00128, "Total": 6.6472057906304, "FillType": "FILL", "OrderType": "BUY", "Uuid": "9776254f-600b-47f0-9cde-6356d3f65d93"}, {"Id": 47163913, "TimeStamp": "2020-01-02T02:10:36.8", "Quantity": 6294.111, "Price": 0.00129, "Total": 8.11940319, "FillType": "FILL", "OrderType": "SELL", "Uuid": "4a54ac2f-41ab-4dfe-929d-4beaafd116e6"}, {"Id": 47163850, "TimeStamp": "2020-01-02T02:08:39.47", "Quantity": 12452.889, "Price": 0.00129, "Total": 16.06422681, "FillType": "FILL", "OrderType": "SELL", "Uuid": "374e941d-85e0-4054-b5d1-4120a7b178fd"}, {"Id": 47154348, "TimeStamp": "2020-01-01T21:28:56", "Quantity": 1713.45032828, "Price": 0.00128, "Total": 2.1932164201984, "FillType": "FILL", "OrderType": "SELL", "Uuid": "2e047ed7-e8d4-41f3-b2b7-910c0dd8a9ac"}, {"Id": 47149143, "TimeStamp": "2020-01-01T18:43:54.71", "Quantity": 175000.0, "Price": 0.00131, "Total": 229.25, "FillType": "FILL", "OrderType": "SELL", "Uuid": "236dbc13-563f-46b7-b740-d88de74af737"}, {"Id": 47144908, "TimeStamp": "2020-01-01T16:48:16.48", "Quantity": 274078.22813611, "Price": 0.00127, "Total": 348.0793497328597, "FillType": "FILL", "OrderType": "BUY", "Uuid": "b0d98297-4bef-4316-85a5-93d33e5b3b75"}, {"Id": 47144907, "TimeStamp": "2020-01-01T16:48:16.23", "Quantity": 25378.97825196, "Price": 0.00127, "Total": 32.2313023799892, "FillType": "FILL", "OrderType": "BUY", "Uuid": "9dc2676c-338f-4686-a947-9afa55690127"}, {"Id": 47144897, "TimeStamp": "2020-01-01T16:48:15.92", "Quantity": 13360.45771892, "Price": 0.00127, "Total": 16.9677813030284, "FillType": "FILL", "OrderType": "BUY", "Uuid": "f465a161-fe58-4aea-afac-14f41d5b2e89"}, {"Id": 47144896, "TimeStamp": "2020-01-01T16:48:15.83", "Quantity": 132095.72432795, "Price": 0.00127, "Total": 167.7615698964965, "FillType": "FILL", "OrderType": "BUY", "Uuid": "e795bd92-7d23-4c4b-a785-2991626922f3"}, {"Id": 47144892, "TimeStamp": "2020-01-01T16:48:15.62", "Quantity": 211057.07852755, "Price": 0.00127, "Total": 268.0424897299885, "FillType": "FILL", "OrderType": "BUY", "Uuid": "f08ecc66-641d-4869-b0ed-8001f101f70a"}, {"Id": 47144883, "TimeStamp": "2020-01-01T16:48:15.37", "Quantity": 335440.96340157, "Price": 0.00127, "Total": 426.0100235199939, "FillType": "FILL", "OrderType": "BUY", "Uuid": "4f83260c-abb2-45fc-9032-c7602d9fead0"}, {"Id": 47144874, "TimeStamp": "2020-01-01T16:48:15.11", "Quantity": 382149.30922047, "Price": 0.00127, "Total": 485.3296227099969, "FillType": "FILL", "OrderType": "BUY", "Uuid": "7a1be7ab-c825-40c5-92d0-9f1f9c0fafd4"}, {"Id": 47144872, "TimeStamp": "2020-01-01T16:48:15.08", "Quantity": 2401.57480314, "Price": 0.00127, "Total": 3.0499999999878, "FillType": "FILL", "OrderType": "BUY", "Uuid": "cb1817a5-dbc6-4a66-9791-c5f033777532"}, {"Id": 47144871, "TimeStamp": "2020-01-01T16:48:14.94", "Quantity": 696006.74915748, "Price": 0.00127, "Total": 883.9285714299996, "FillType": "FILL", "OrderType": "SELL", "Uuid": "6e79e23a-020e-43cc-9b72-673da51f2813"}, {"Id": 47126299, "TimeStamp": "2020-01-01T04:22:05.75", "Quantity": 17485.0012669, "Price": 0.00139, "Total": 24.304151760991, "FillType": "FILL", "OrderType": "BUY", "Uuid": "1bbb4e7a-1dc4-404b-9ea6-e2952eb81949"}, {"Id": 47126298, "TimeStamp": "2020-01-01T04:22:05.75", "Quantity": 13352.0027331, "Price": 0.00132, "Total": 17.624643607692, "FillType": "FILL", "OrderType": "BUY", "Uuid": "4d73abab-1f9a-4577-b1cd-28af0a88b53f"}, {"Id": 47126117, "TimeStamp": "2020-01-01T04:12:41.29", "Quantity": 1431.07972224, "Price": 0.00126, "Total": 1.8031604500224, "FillType": "FILL", "OrderType": "SELL", "Uuid": "0bf43e56-0037-4c59-b65e-3e88017c3153"}, {"Id": 47126116, "TimeStamp": "2020-01-01T04:12:41.29", "Quantity": 7874.01574803, "Price": 0.00127, "Total": 9.9999999999981, "FillType": "FILL", "OrderType": "SELL", "Uuid": "d31cce2b-92ba-4549-96a7-af7eaab75341"}, {"Id": 47076925, "TimeStamp": "2019-12-31T06:58:07.03", "Quantity": 7692.30769231, "Price": 0.0013, "Total": 10.000000000003, "FillType": "FILL", "OrderType": "SELL", "Uuid": "e56d5218-885e-42b2-b886-d7e03a1156f8"}, {"Id": 47076924, "TimeStamp": "2019-12-31T06:58:07.03", "Quantity": 50005.0, "Price": 0.0013, "Total": 65.0065, "FillType": "FILL", "OrderType": "SELL", "Uuid": "8696295b-b174-4d37-ac4b-395d06367e89"}, {"Id": 47074412, "TimeStamp": "2019-12-31T05:37:57.91", "Quantity": 28.02789849, "Price": 0.00132, "Total": 0.0369968260068, "FillType": "FILL", "OrderType": "SELL", "Uuid": "f20f781b-45c6-4af0-89fc-ea22c5d8a1fc"}, {"Id": 47074403, "TimeStamp": "2019-12-31T05:37:57.86", "Quantity": 9604.72663858, "Price": 0.00132, "Total": 12.6782391629256, "FillType": "FILL", "OrderType": "SELL", "Uuid": "c11919fe-828b-4d45-8900-f005fd78eb80"}, {"Id": 47065716, "TimeStamp": "2019-12-31T00:31:13.61", "Quantity": 5074.19189394, "Price": 0.00132, "Total": 6.6979333000008, "FillType": "FILL", "OrderType": "SELL", "Uuid": "dc81eb0e-7cec-4132-bc05-6ff62614f8df"}, {"Id": 47065711, "TimeStamp": "2019-12-31T00:31:08.02", "Quantity": 3850.07006549, "Price": 0.00132, "Total": 5.0820924864468, "FillType": "FILL", "OrderType": "SELL", "Uuid": "baa8d647-a6fc-4411-8c2e-d20075e41635"}, {"Id": 47065704, "TimeStamp": "2019-12-31T00:31:03.77", "Quantity": 3829.10363648, "Price": 0.00134, "Total": 5.1309988728832, "FillType": "FILL", "OrderType": "SELL", "Uuid": "ab379fee-5e9c-4487-86b5-f42a9972034e"}, {"Id": 47065703, "TimeStamp": "2019-12-31T00:31:03.61", "Quantity": 1170.89636352, "Price": 0.00134, "Total": 1.5690011271168, "FillType": "FILL", "OrderType": "BUY", "Uuid": "59740804-0846-44c0-b718-ba3ed3b65912"}, {"Id": 47044159, "TimeStamp": "2019-12-30T17:31:52.56", "Quantity": 11509.61538462, "Price": 0.00132, "Total": 15.1926923076984, "FillType": "FILL", "OrderType": "SELL", "Uuid": "93f3f25c-5b08-45cb-b3e0-b74d5a7f22c5"}, {"Id": 47041217, "TimeStamp": "2019-12-30T16:06:50.93", "Quantity": 2000.0, "Price": 0.00132, "Total": 2.64, "FillType": "FILL", "OrderType": "SELL", "Uuid": "bdcd753b-c318-4e56-8098-db6f779da908"}, {"Id": 47037744, "TimeStamp": "2019-12-30T14:49:26.91", "Quantity": 5153.75, "Price": 0.00132, "Total": 6.80295, "FillType": "FILL", "OrderType": "SELL", "Uuid": "f1a8c688-3534-49d0-a606-b16d0bf0baec"}, {"Id": 47034876, "TimeStamp": "2019-12-30T13:30:24.45", "Quantity": 37858.93, "Price": 0.00134, "Total": 50.7309662, "FillType": "FILL", "OrderType": "BUY", "Uuid": "56844795-b1e5-4147-aae6-707d12d8cb9b"}, {"Id": 47034875, "TimeStamp": "2019-12-30T13:30:23.39", "Quantity": 88033.0, "Price": 0.00134, "Total": 117.96422, "FillType": "FILL", "OrderType": "SELL", "Uuid": "4f74d153-7cea-42b4-b628-b859a0af5843"}, {"Id": 46991534, "TimeStamp": "2019-12-29T19:27:18.77", "Quantity": 8.79053406, "Price": 0.00135, "Total": 0.011867220981, "FillType": "FILL", "OrderType": "SELL", "Uuid": "aa66322e-7c31-4568-938f-2cdc23b435ad"}, {"Id": 46991533, "TimeStamp": "2019-12-29T19:27:18.77", "Quantity": 4249.0, "Price": 0.00137, "Total": 5.82113, "FillType": "FILL", "OrderType": "SELL", "Uuid": "7a01ac71-9090-4a0f-9af3-e6ccfd5442f9"}, {"Id": 46982909, "TimeStamp": "2019-12-29T15:50:30.31", "Quantity": 7805.26728791, "Price": 0.0014, "Total": 10.927374203074, "FillType": "FILL", "OrderType": "BUY", "Uuid": "8c0c5c2a-6d7c-49b2-a181-39407a6a0a0d"}, {"Id": 46982891, "TimeStamp": "2019-12-29T15:50:28.22", "Quantity": 18900.64113764, "Price": 0.00137, "Total": 25.8938783585668, "FillType": "FILL", "OrderType": "BUY", "Uuid": "f6150349-8ac3-4027-9ef4-88845ec8216b"}, {"Id": 46982876, "TimeStamp": "2019-12-29T15:50:27.33", "Quantity": 7805.26728791, "Price": 0.00137, "Total": 10.6932161844367, "FillType": "FILL", "OrderType": "BUY", "Uuid": "399a7384-4101-4b03-8ddb-f3d44c59e4ea"}, {"Id": 46982874, "TimeStamp": "2019-12-29T15:50:27.14", "Quantity": 7805.26728791, "Price": 0.00137, "Total": 10.6932161844367, "FillType": "FILL", "OrderType": "BUY", "Uuid": "d383d606-ade4-4906-96f4-fcbefee759f8"}, {"Id": 46982853, "TimeStamp": "2019-12-29T15:50:23.02", "Quantity": 7810.13570164, "Price": 0.00137, "Total": 10.6998859112468, "FillType": "FILL", "OrderType": "BUY", "Uuid": "de6452f0-8958-4c84-89be-2552c98e1979"}, {"Id": 46982851, "TimeStamp": "2019-12-29T15:50:22.95", "Quantity": 7810.13570164, "Price": 0.00137, "Total": 10.6998859112468, "FillType": "FILL", "OrderType": "BUY", "Uuid": "0846c118-cc61-4d33-bb41-043b6188d3c7"}, {"Id": 46980400, "TimeStamp": "2019-12-29T14:34:43.62", "Quantity": 36405.33702241, "Price": 0.00137, "Total": 49.8753117207017, "FillType": "FILL", "OrderType": "BUY", "Uuid": "0864188d-1478-4414-b08d-1794b96565a5"}, {"Id": 46976135, "TimeStamp": "2019-12-29T12:58:02.73", "Quantity": 10109.00991026, "Price": 0.00136, "Total": 13.7482534779536, "FillType": "FILL", "OrderType": "BUY", "Uuid": "c6da8af7-b560-4946-958a-e430e5cfa503"}, {"Id": 46976112, "TimeStamp": "2019-12-29T12:57:30.88", "Quantity": 8141.92370937, "Price": 0.00136, "Total": 11.0730162447432, "FillType": "FILL", "OrderType": "BUY", "Uuid": "df98b80b-3c57-4f1c-b3ef-9df617dc61ed"}, {"Id": 46968028, "TimeStamp": "2019-12-29T08:53:42.54", "Quantity": 981.85456719, "Price": 0.00134, "Total": 1.3156851200346, "FillType": "FILL", "OrderType": "BUY", "Uuid": "e17df454-4f75-4f9e-ba74-a14acd41e2ab"}, {"Id": 46954000, "TimeStamp": "2019-12-29T00:50:34.94", "Quantity": 20042.12613214, "Price": 0.00133, "Total": 26.6560277557462, "FillType": "FILL", "OrderType": "SELL", "Uuid": "547d5142-4500-4632-8ce6-8ddbecd5bf7a"}, {"Id": 46953990, "TimeStamp": "2019-12-29T00:50:14.27", "Quantity": 20819.96607791, "Price": 0.00133, "Total": 27.6905548836203, "FillType": "FILL", "OrderType": "BUY", "Uuid": "73b51f08-91e6-4d57-a74d-a02ce332a1a5"}, {"Id": 46953986, "TimeStamp": "2019-12-29T00:50:13.47", "Quantity": 14981.92492201, "Price": 0.00133, "Total": 19.9259601462733, "FillType": "FILL", "OrderType": "BUY", "Uuid": "8904d94c-64f7-476e-a3ac-15be0c1d9f9d"}, {"Id": 46953982, "TimeStamp": "2019-12-29T00:50:13", "Quantity": 89198.10900008, "Price": 0.00133, "Total": 118.6334849701064, "FillType": "FILL", "OrderType": "BUY", "Uuid": "ac9c9bec-1280-47b7-9677-55c89a1d2bcb"}, {"Id": 46953976, "TimeStamp": "2019-12-29T00:50:03.41", "Quantity": 125000.0, "Price": 0.00133, "Total": 166.25, "FillType": "FILL", "OrderType": "SELL", "Uuid": "9d124e7a-289c-4d8f-8e28-828d571138ec"}, {"Id": 46953971, "TimeStamp": "2019-12-29T00:49:57.14", "Quantity": 40000.0, "Price": 0.00133, "Total": 53.2, "FillType": "FILL", "OrderType": "BUY", "Uuid": "7ef80250-493f-4242-908d-d6b61455e405"}, {"Id": 46953957, "TimeStamp": "2019-12-29T00:49:56.32", "Quantity": 53615.82296317, "Price": 0.00133, "Total": 71.3090445410161, "FillType": "FILL", "OrderType": "SELL", "Uuid": "fef08856-ddc4-4b2b-b370-ade37c5e410f"}, {"Id": 46953956, "TimeStamp": "2019-12-29T00:49:56.32", "Quantity": 40544.75090469, "Price": 0.00133, "Total": 53.9245187032377, "FillType": "FILL", "OrderType": "SELL", "Uuid": "fbcfaefc-3d7f-446a-93c6-d9ba299ac373"}, {"Id": 46951147, "TimeStamp": "2019-12-28T23:26:23.04", "Quantity": 2000.0, "Price": 0.00133, "Total": 2.66, "FillType": "FILL", "OrderType": "SELL", "Uuid": "3b8f5dd8-df0d-4413-a2f4-c04e43aace51"}, {"Id": 46938983, "TimeStamp": "2019-12-28T16:40:28.73", "Quantity": 31746.64, "Price": 0.00134, "Total": 42.5404976, "FillType": "FILL", "OrderType": "BUY", "Uuid": "3abc4d20-200e-49dc-8844-e41b43b521ba"}, {"Id": 46933867, "TimeStamp": "2019-12-28T14:15:40.08", "Quantity": 9204.131292, "Price": 0.00134, "Total": 12.33353593128, "FillType": "FILL", "OrderType": "BUY", "Uuid": "88c8a5f5-6bcf-4c1e-b962-06ff7f712c88"}, {"Id": 46933863, "TimeStamp": "2019-12-28T14:15:39.99", "Quantity": 9204.131292, "Price": 0.00134, "Total": 12.33353593128, "FillType": "FILL", "OrderType": "BUY", "Uuid": "c30fc624-7278-4205-b341-4e36f8693377"}, {"Id": 46933858, "TimeStamp": "2019-12-28T14:15:39.26", "Quantity": 8655.24284881, "Price": 0.00134, "Total": 11.5980254174054, "FillType": "FILL", "OrderType": "BUY", "Uuid": "ade981fd-3c34-4559-a9a6-4b83b8942f37"}, {"Id": 46915058, "TimeStamp": "2019-12-28T04:16:04.66", "Quantity": 38110.11648568, "Price": 0.00134, "Total": 51.0675560908112, "FillType": "FILL", "OrderType": "SELL", "Uuid": "54251ece-8f3e-4f6e-8063-4280c30f83a2"}, {"Id": 46909771, "TimeStamp": "2019-12-28T01:00:52.03", "Quantity": 1220.05146486, "Price": 0.00134, "Total": 1.6348689629124, "FillType": "FILL", "OrderType": "BUY", "Uuid": "c82b25d7-8739-4535-be88-b7ce4949a99a"}, {"Id": 46908998, "TimeStamp": "2019-12-28T00:40:03.54", "Quantity": 7174.40365093, "Price": 0.00134, "Total": 9.6137008922462, "FillType": "FILL", "OrderType": "BUY", "Uuid": "7ad8a78c-63bf-46ed-8093-7b82d170c3dc"}, {"Id": 46907882, "TimeStamp": "2019-12-28T00:15:02.34", "Quantity": 1539.3252193, "Price": 0.00134, "Total": 2.062695793862, "FillType": "FILL", "OrderType": "BUY", "Uuid": "be9755d5-201f-4be3-a6eb-7a373f63cee0"}, {"Id": 46903663, "TimeStamp": "2019-12-27T22:02:47.96", "Quantity": 4468.94776491, "Price": 0.00134, "Total": 5.9883900049794, "FillType": "FILL", "OrderType": "BUY", "Uuid": "4705f3a8-6f11-4de7-a852-c8d268d07c9a"}, {"Id": 46896310, "TimeStamp": "2019-12-27T18:00:25.1", "Quantity": 1500.0, "Price": 0.00131, "Total": 1.965, "FillType": "FILL", "OrderType": "BUY", "Uuid": "88ff17ad-f4b1-4763-88c6-7afab0a33b20"}, {"Id": 46880229, "TimeStamp": "2019-12-27T11:24:53.93", "Quantity": 204618.099169, "Price": 0.0013, "Total": 266.0035289197, "FillType": "FILL", "OrderType": "BUY", "Uuid": "e9a0f469-3d98-491f-8d7e-f6df0bfb51e3"}, {"Id": 46880224, "TimeStamp": "2019-12-27T11:24:53.77", "Quantity": 34337.0681606, "Price": 0.0013, "Total": 44.63818860878, "FillType": "FILL", "OrderType": "BUY", "Uuid": "db8c47c0-7dc8-44af-b845-dc246d9da1a0"}, {"Id": 46880223, "TimeStamp": "2019-12-27T11:24:53.76", "Quantity": 7523.07692307, "Price": 0.0013, "Total": 9.779999999991, "FillType": "FILL", "OrderType": "BUY", "Uuid": "20106b0a-33a6-4277-9a15-5f2de7eb2e44"}, {"Id": 46880220, "TimeStamp": "2019-12-27T11:24:53.51", "Quantity": 9114.68990374, "Price": 0.0013, "Total": 11.849096874862, "FillType": "FILL", "OrderType": "SELL", "Uuid": "3a33a8b6-dbe8-4995-97d6-18802246cd65"}, {"Id": 46880219, "TimeStamp": "2019-12-27T11:24:53.51", "Quantity": 9114.68990374, "Price": 0.0013, "Total": 11.849096874862, "FillType": "FILL", "OrderType": "SELL", "Uuid": "55f586ff-92d4-40f5-8fe6-b43180241d29"}, {"Id": 46880218, "TimeStamp": "2019-12-27T11:24:53.51", "Quantity": 75750.37593985, "Price": 0.00132, "Total": 99.990496240602, "FillType": "FILL", "OrderType": "SELL", "Uuid": "46ddb424-b2d1-4286-93b6-0b5ba1e7726e"}, {"Id": 46864069, "TimeStamp": "2019-12-27T02:14:27.13", "Quantity": 5000.0, "Price": 0.00135, "Total": 6.75, "FillType": "FILL", "OrderType": "BUY", "Uuid": "606eeb4f-328f-4ccf-9536-7dc4751c6e14"}, {"Id": 46864068, "TimeStamp": "2019-12-27T02:14:27.13", "Quantity": 5000.0, "Price": 0.00135, "Total": 6.75, "FillType": "FILL", "OrderType": "BUY", "Uuid": "a27c7177-8172-49f3-a878-df148535bce1"}, {"Id": 46832782, "TimeStamp": "2019-12-26T14:11:08.55", "Quantity": 35135.13513514, "Price": 0.00138, "Total": 48.4864864864932, "FillType": "FILL", "OrderType": "BUY", "Uuid": "a0820456-a1ac-48a8-adb4-f8d9b7273d14"}], "timestamp": 1578199658.5931456}