{"success": true, "message": "", "result": [{"Id": 48007468, "TimeStamp": "2020-01-05T04:50:02.46", "Quantity": 2.51779798, "Price": 0.000125, "Total": 0.0003147247475, "FillType": "FILL", "OrderType": "SELL", "Uuid": "fce28fdb-7469-47c5-a76b-74109b0ebac7"}, {"Id": 48007467, "TimeStamp": "2020-01-05T04:49:59.91", "Quantity": 10.0, "Price": 0.000125, "Total": 0.00125, "FillType": "FILL", "OrderType": "SELL", "Uuid": "543ff6fa-3a92-4e26-80fd-688722074bf2"}, {"Id": 48007464, "TimeStamp": "2020-01-05T04:49:58.82", "Quantity": 15.0, "Price": 0.000125, "Total": 0.001875, "FillType": "FILL", "OrderType": "SELL", "Uuid": "f33b2835-cde0-48ce-aaf5-2bfdcd2ac9af"}, {"Id": 48007463, "TimeStamp": "2020-01-05T04:49:58.8", "Quantity": 10.56, "Price": 0.000125, "Total": 0.00132, "FillType": "FILL", "OrderType": "SELL", "Uuid": "7a32d414-8861-4546-a7e4-2f301422fe50"}, {"Id": 48007441, "TimeStamp": "2020-01-05T04:49:22.62", "Quantity": 14.0, "Price": 0.000125, "Total": 0.00175, "FillType": "FILL", "OrderType": "SELL", "Uuid": "c54ee8ed-167a-476f-86d9-584ef703d160"}, {"Id": 48007300, "TimeStamp": "2020-01-05T04:43:57.94", "Quantity": 15.5853716, "Price": 0.00012597, "Total": 0.001963289260452, "FillType": "FILL", "OrderType": "BUY", "Uuid": "93a00c95-c276-4a5d-aa49-806b17ea36b7"}, {"Id": 48007057, "TimeStamp": "2020-01-05T04:37:19", "Quantity": 29.06258627, "Price": 0.00012512, "Total": 0.0036363107941024, "FillType": "FILL", "OrderType": "BUY", "Uuid": "01f063e8-772d-4905-a0fa-ba4885277d76"}, {"Id": 48006941, "TimeStamp": "2020-01-05T04:33:31.19", "Quantity": 31.95, "Price": 0.000125, "Total": 0.00399375, "FillType": "FILL", "OrderType": "SELL", "Uuid": "3e3f798a-e85e-4ed5-8f95-de99ec665087"}, {"Id": 48006939, "TimeStamp": "2020-01-05T04:33:27.92", "Quantity": 28.63581291, "Price": 0.000125, "Total": 0.00357947661375, "FillType": "FILL", "OrderType": "SELL", "Uuid": "70f66dfa-4133-4464-bdc4-2df85e2c69a2"}, {"Id": 48006938, "TimeStamp": "2020-01-05T04:33:27.92", "Quantity": 2.56418709, "Price": 0.000125, "Total": 0.00032052338625, "FillType": "FILL", "OrderType": "SELL", "Uuid": "9a171943-1893-4c0e-8407-88d8d2abb892"}, {"Id": 48006895, "TimeStamp": "2020-01-05T04:32:04.41", "Quantity": 27.16130921, "Price": 0.00012538, "Total": 0.0034054849487498, "FillType": "FILL", "OrderType": "BUY", "Uuid": "21ca5dd2-8e8c-4f90-96a3-d6f5ecfb0cfb"}, {"Id": 48006206, "TimeStamp": "2020-01-05T04:06:37.11", "Quantity": 40.19, "Price": 0.000125, "Total": 0.00502375, "FillType": "FILL", "OrderType": "SELL", "Uuid": "d5dc969f-a17f-48de-981e-7a0880a3792b"}, {"Id": 48006098, "TimeStamp": "2020-01-05T04:05:21.22", "Quantity": 11.98, "Price": 0.000125, "Total": 0.0014975, "FillType": "FILL", "OrderType": "SELL", "Uuid": "ee4c868a-b29d-488e-955d-2d5b9dea612d"}, {"Id": 48006066, "TimeStamp": "2020-01-05T04:05:02.94", "Quantity": 20.7, "Price": 0.000125, "Total": 0.0025875, "FillType": "FILL", "OrderType": "SELL", "Uuid": "4bd7942e-a4b3-441c-8585-bfeefc7701e0"}, {"Id": 48006060, "TimeStamp": "2020-01-05T04:04:58.85", "Quantity": 20.7, "Price": 0.000125, "Total": 0.0025875, "FillType": "FILL", "OrderType": "SELL", "Uuid": "749b2e14-3454-45dc-8804-ec197be9c8b1"}, {"Id": 48006055, "TimeStamp": "2020-01-05T04:04:55.85", "Quantity": 20.7, "Price": 0.000125, "Total": 0.0025875, "FillType": "FILL", "OrderType": "SELL", "Uuid": "09c10e3f-8c67-497d-9915-793e0396e9e8"}, {"Id": 48006049, "TimeStamp": "2020-01-05T04:04:53.41", "Quantity": 20.7, "Price": 0.000125, "Total": 0.0025875, "FillType": "FILL", "OrderType": "SELL", "Uuid": "b2914f1d-4f9f-41f2-9087-4d957289186b"}, {"Id": 48006038, "TimeStamp": "2020-01-05T04:04:48.3", "Quantity": 20.7, "Price": 0.000125, "Total": 0.0025875, "FillType": "FILL", "OrderType": "SELL", "Uuid": "dbb93f07-591b-488e-ba20-a861d9c9f79d"}, {"Id": 48006031, "TimeStamp": "2020-01-05T04:04:44.91", "Quantity": 20.7, "Price": 0.000125, "Total": 0.0025875, "FillType": "FILL", "OrderType": "SELL", "Uuid": "134af4ec-4805-4479-85e9-12da901c6cc3"}, {"Id": 48006016, "TimeStamp": "2020-01-05T04:04:38.25", "Quantity": 20.7, "Price": 0.000125, "Total": 0.0025875, "FillType": "FILL", "OrderType": "SELL", "Uuid": "556ec835-075b-4363-bc46-cc8fa829ffcd"}, {"Id": 48006010, "TimeStamp": "2020-01-05T04:04:34.77", "Quantity": 20.7, "Price": 0.000125, "Total": 0.0025875, "FillType": "FILL", "OrderType": "SELL", "Uuid": "485c608f-2a04-4243-b83d-c4cebdbb69d4"}, {"Id": 48006005, "TimeStamp": "2020-01-05T04:04:31.11", "Quantity": 20.7, "Price": 0.000125, "Total": 0.0025875, "FillType": "FILL", "OrderType": "SELL", "Uuid": "d763c41a-81a7-4a9b-bd58-5d14d7420ac2"}, {"Id": 48005934, "TimeStamp": "2020-01-05T04:03:46.56", "Quantity": 10.984622, "Price": 0.000125, "Total": 0.00137307775, "FillType": "FILL", "OrderType": "SELL", "Uuid": "c64b33b5-c0e0-4205-adc2-0317b679fa19"}, {"Id": 48005855, "TimeStamp": "2020-01-05T04:02:59.1", "Quantity": 8.36999, "Price": 0.000125, "Total": 0.00104624875, "FillType": "FILL", "OrderType": "SELL", "Uuid": "db577a1f-f3e1-422d-9ac6-982851921857"}, {"Id": 48005846, "TimeStamp": "2020-01-05T04:02:52.22", "Quantity": 12.33, "Price": 0.000125, "Total": 0.00154125, "FillType": "FILL", "OrderType": "SELL", "Uuid": "3a1d29a9-025f-4d43-8cda-4bb8bc8236fe"}, {"Id": 48005816, "TimeStamp": "2020-01-05T04:02:36.35", "Quantity": 20.7, "Price": 0.000125, "Total": 0.0025875, "FillType": "FILL", "OrderType": "SELL", "Uuid": "bb8a8e7c-9885-4378-8e5b-02938cb9c9da"}, {"Id": 48005357, "TimeStamp": "2020-01-05T04:00:50.44", "Quantity": 160.0, "Price": 0.000125, "Total": 0.02, "FillType": "FILL", "OrderType": "SELL", "Uuid": "bfd75026-7572-4888-ab33-c33b95ef6a94"}, {"Id": 48005276, "TimeStamp": "2020-01-05T04:00:27.11", "Quantity": 16.2, "Price": 0.000125, "Total": 0.002025, "FillType": "FILL", "OrderType": "SELL", "Uuid": "9e2379e5-74f8-41d9-aecc-79da00b62e50"}, {"Id": 48004759, "TimeStamp": "2020-01-05T03:55:31.37", "Quantity": 31.77629488, "Price": 0.00012587, "Total": 0.0039996822365456, "FillType": "FILL", "OrderType": "BUY", "Uuid": "79ddb444-9ecf-4e0a-a74d-9d99d119d7cb"}, {"Id": 48004427, "TimeStamp": "2020-01-05T03:49:48.54", "Quantity": 22.93179475, "Price": 0.00012609, "Total": 0.0028914700000275, "FillType": "FILL", "OrderType": "BUY", "Uuid": "d80a50cb-b574-4ab9-899c-ed71d8309787"}, {"Id": 48003400, "TimeStamp": "2020-01-05T03:27:27.47", "Quantity": 153.37222801, "Price": 0.000125, "Total": 0.01917152850125, "FillType": "FILL", "OrderType": "SELL", "Uuid": "cf633976-2e55-4f55-b5e7-57a09998dff4"}, {"Id": 48002942, "TimeStamp": "2020-01-05T03:10:28.43", "Quantity": 192.29798546, "Price": 0.000125, "Total": 0.0240372481825, "FillType": "FILL", "OrderType": "SELL", "Uuid": "c8752555-4e6d-4ea4-97ce-b533e8cd6b17"}, {"Id": 48002941, "TimeStamp": "2020-01-05T03:10:28.43", "Quantity": 23.9, "Price": 0.0001251, "Total": 0.00298989, "FillType": "FILL", "OrderType": "SELL", "Uuid": "e1ee27fe-27b9-4374-a7e6-424f6eb447a7"}, {"Id": 48002915, "TimeStamp": "2020-01-05T03:08:02.09", "Quantity": 160.0, "Price": 0.000125, "Total": 0.02, "FillType": "FILL", "OrderType": "SELL", "Uuid": "8240a4d5-b468-4ef1-97a1-c4e99766b74d"}, {"Id": 48002900, "TimeStamp": "2020-01-05T03:07:18.49", "Quantity": 15.58035851, "Price": 0.000125, "Total": 0.00194754481375, "FillType": "FILL", "OrderType": "SELL", "Uuid": "08cbc783-006a-47c2-9a7e-4f5f60d9c2c0"}, {"Id": 48002895, "TimeStamp": "2020-01-05T03:06:57.12", "Quantity": 9.13062893, "Price": 0.000125, "Total": 0.00114132861625, "FillType": "FILL", "OrderType": "SELL", "Uuid": "af7d6843-23c2-473a-899b-bac64e14ee93"}, {"Id": 48002894, "TimeStamp": "2020-01-05T03:06:57.12", "Quantity": 7.06937107, "Price": 0.000125, "Total": 0.00088367138375, "FillType": "FILL", "OrderType": "SELL", "Uuid": "d3b7b285-251c-4b54-bfe0-4db13bcd31ae"}, {"Id": 48002855, "TimeStamp": "2020-01-05T03:05:23.13", "Quantity": 9.9, "Price": 0.00012566, "Total": 0.001244034, "FillType": "FILL", "OrderType": "BUY", "Uuid": "c8c0cbe4-9076-46ef-bc8f-c1c03341936b"}, {"Id": 48001742, "TimeStamp": "2020-01-05T02:16:16.14", "Quantity": 8.02797869, "Price": 0.00012581, "Total": 0.0010099999989889, "FillType": "FILL", "OrderType": "BUY", "Uuid": "7e0ca9fc-d05f-4a3c-8d57-83c04f122e0c"}, {"Id": 48001741, "TimeStamp": "2020-01-05T02:16:13.55", "Quantity": 0.9106788, "Price": 0.000125, "Total": 0.00011383485, "FillType": "FILL", "OrderType": "SELL", "Uuid": "58928d50-e054-4740-93cd-824dff4792fe"}, {"Id": 48001740, "TimeStamp": "2020-01-05T02:16:13.55", "Quantity": 4.9093212, "Price": 0.00012501, "Total": 0.000613714243212, "FillType": "FILL", "OrderType": "SELL", "Uuid": "d2abe2f3-c700-452d-accd-66ed23816870"}, {"Id": 48001620, "TimeStamp": "2020-01-05T02:09:48.78", "Quantity": 7.4, "Price": 0.00012509, "Total": 0.000925666, "FillType": "FILL", "OrderType": "BUY", "Uuid": "03471d5e-a95b-4240-95ec-9465c72e1ad9"}, {"Id": 48001540, "TimeStamp": "2020-01-05T02:05:54.78", "Quantity": 38.8, "Price": 0.00012501, "Total": 0.004850388, "FillType": "FILL", "OrderType": "SELL", "Uuid": "01ffce0e-ba46-4678-98da-64a0965d8066"}, {"Id": 48001537, "TimeStamp": "2020-01-05T02:05:50.56", "Quantity": 0.00857285, "Price": 0.000126, "Total": 1.0801791e-06, "FillType": "FILL", "OrderType": "SELL", "Uuid": "f337451a-e883-4a6a-a0da-e9677b8f07b1"}, {"Id": 48001436, "TimeStamp": "2020-01-05T02:03:24.17", "Quantity": 4.02, "Price": 0.000126, "Total": 0.00050652, "FillType": "FILL", "OrderType": "SELL", "Uuid": "513f357b-de81-4b60-89e0-602a08b6eb86"}, {"Id": 48001359, "TimeStamp": "2020-01-05T02:01:29.48", "Quantity": 200.0, "Price": 0.0001254, "Total": 0.02508, "FillType": "FILL", "OrderType": "SELL", "Uuid": "ac234966-03dc-4973-8267-4f25956fc747"}, {"Id": 48001358, "TimeStamp": "2020-01-05T02:01:29.48", "Quantity": 8.8951, "Price": 0.00012541, "Total": 0.001115534491, "FillType": "FILL", "OrderType": "SELL", "Uuid": "8496560a-c98a-4c6a-8029-1f98eebae955"}, {"Id": 48001357, "TimeStamp": "2020-01-05T02:01:29.48", "Quantity": 23.89676597, "Price": 0.00012554, "Total": 0.0029999999998738, "FillType": "FILL", "OrderType": "SELL", "Uuid": "469d7cf9-ad94-4f66-8d3a-44598e26190e"}, {"Id": 48001356, "TimeStamp": "2020-01-05T02:01:29.48", "Quantity": 4.79863924, "Price": 0.00012578, "Total": 0.0006035728436072, "FillType": "FILL", "OrderType": "SELL", "Uuid": "fe59959c-35d1-4745-b7fd-825c2e950ac0"}, {"Id": 48000892, "TimeStamp": "2020-01-05T01:39:48.66", "Quantity": 10.90551429, "Price": 0.00012657, "Total": 0.0013803109436853, "FillType": "FILL", "OrderType": "BUY", "Uuid": "4292c4b6-3aa5-47c4-98d4-76cea2616941"}, {"Id": 48000509, "TimeStamp": "2020-01-05T01:27:21.74", "Quantity": 7.12694511, "Price": 0.00012578, "Total": 0.0008964271559358, "FillType": "FILL", "OrderType": "SELL", "Uuid": "381b0748-cf58-481b-8ecb-b51cb5b50dec"}, {"Id": 48000508, "TimeStamp": "2020-01-05T01:27:21.74", "Quantity": 0.00305489, "Price": 0.00012584, "Total": 3.844273576e-07, "FillType": "FILL", "OrderType": "SELL", "Uuid": "100ffbbc-fa79-4d87-b654-248eeff60b24"}, {"Id": 48000490, "TimeStamp": "2020-01-05T01:26:59.7", "Quantity": 7.13, "Price": 0.00012584, "Total": 0.0008972392, "FillType": "FILL", "OrderType": "SELL", "Uuid": "b029e105-2ec5-4537-a309-99f26cf7e906"}, {"Id": 48000423, "TimeStamp": "2020-01-05T01:26:08.21", "Quantity": 6.35746031, "Price": 0.000126, "Total": 0.00080103999906, "FillType": "FILL", "OrderType": "SELL", "Uuid": "ef3bec99-cec7-4af7-ad64-93a67f6012a0"}, {"Id": 48000419, "TimeStamp": "2020-01-05T01:26:07.35", "Quantity": 17.05437229, "Price": 0.00012611, "Total": 0.0021507268894919, "FillType": "FILL", "OrderType": "SELL", "Uuid": "5b386b21-3f43-4d02-9125-5d82482b8a9f"}, {"Id": 48000418, "TimeStamp": "2020-01-05T01:26:07.35", "Quantity": 31.71582619, "Price": 0.00012612, "Total": 0.0039999999990828, "FillType": "FILL", "OrderType": "SELL", "Uuid": "51bdc686-93e2-4aec-948a-c2af8aae2063"}, {"Id": 48000191, "TimeStamp": "2020-01-05T01:23:02.04", "Quantity": 2.0156939, "Price": 0.00012653, "Total": 0.000255045749167, "FillType": "FILL", "OrderType": "BUY", "Uuid": "6ae1885c-f8da-4173-a550-ad0a3124b519"}, {"Id": 48000190, "TimeStamp": "2020-01-05T01:23:02.04", "Quantity": 15.6, "Price": 0.00012653, "Total": 0.001973868, "FillType": "FILL", "OrderType": "BUY", "Uuid": "7e6ddd9b-4ed8-46dc-ade4-e430eb3d93a9"}, {"Id": 48000171, "TimeStamp": "2020-01-05T01:22:56.07", "Quantity": 15.6, "Price": 0.00012642, "Total": 0.001972152, "FillType": "FILL", "OrderType": "BUY", "Uuid": "b47f7c88-0ae3-45c5-a244-608cef7f9ea2"}, {"Id": 48000114, "TimeStamp": "2020-01-05T01:21:20.24", "Quantity": 20.0, "Price": 0.00012613, "Total": 0.0025226, "FillType": "FILL", "OrderType": "SELL", "Uuid": "70c618e6-f77a-4ee0-be39-32059e3f169f"}, {"Id": 48000088, "TimeStamp": "2020-01-05T01:20:47.47", "Quantity": 278.35, "Price": 0.00012618, "Total": 0.035122203, "FillType": "FILL", "OrderType": "SELL", "Uuid": "7e86d70b-2204-489a-a14a-beefa4810a47"}, {"Id": 48000085, "TimeStamp": "2020-01-05T01:20:46.16", "Quantity": 100.68, "Price": 0.00012618, "Total": 0.0127038024, "FillType": "FILL", "OrderType": "SELL", "Uuid": "1e22adca-51fc-487b-8469-819833e6dac7"}, {"Id": 48000084, "TimeStamp": "2020-01-05T01:20:46.16", "Quantity": 19.83041451, "Price": 0.00012699, "Total": 0.0025182643386249, "FillType": "FILL", "OrderType": "SELL", "Uuid": "36447f20-86ec-4e36-922c-7b3c3fc11c5e"}, {"Id": 48000083, "TimeStamp": "2020-01-05T01:20:46.16", "Quantity": 600.0, "Price": 0.00012722, "Total": 0.076332, "FillType": "FILL", "OrderType": "SELL", "Uuid": "e80df996-0784-4c26-a81b-d18d72cd28a9"}, {"Id": 48000082, "TimeStamp": "2020-01-05T01:20:46.16", "Quantity": 19.59309267, "Price": 0.0001273, "Total": 0.002494200696891, "FillType": "FILL", "OrderType": "SELL", "Uuid": "307d1578-5309-47b9-bfa5-f13f25d39f13"}, {"Id": 48000081, "TimeStamp": "2020-01-05T01:20:46", "Quantity": 100.68, "Price": 0.0001273, "Total": 0.012816564, "FillType": "FILL", "OrderType": "SELL", "Uuid": "0d690a69-6461-4971-8a5b-83573dc55b1f"}, {"Id": 48000079, "TimeStamp": "2020-01-05T01:20:44.24", "Quantity": 35.9733, "Price": 0.0001273, "Total": 0.00457940109, "FillType": "FILL", "OrderType": "SELL", "Uuid": "a2df92fe-117a-4cb5-824a-f6186c538767"}, {"Id": 48000077, "TimeStamp": "2020-01-05T01:20:44.07", "Quantity": 31.2, "Price": 0.0001273, "Total": 0.00397176, "FillType": "FILL", "OrderType": "SELL", "Uuid": "fe1cd8a5-705b-452e-9db0-6330ff2cbc5a"}, {"Id": 48000075, "TimeStamp": "2020-01-05T01:20:41.55", "Quantity": 29.6, "Price": 0.0001273, "Total": 0.00376808, "FillType": "FILL", "OrderType": "SELL", "Uuid": "70fc1c77-9a70-4582-bc7c-374f4971f321"}, {"Id": 48000061, "TimeStamp": "2020-01-05T01:20:37.05", "Quantity": 31.2, "Price": 0.0001273, "Total": 0.00397176, "FillType": "FILL", "OrderType": "SELL", "Uuid": "f9e65779-71fe-4419-ad56-b4229085d3aa"}, {"Id": 48000053, "TimeStamp": "2020-01-05T01:20:31.18", "Quantity": 31.2, "Price": 0.0001273, "Total": 0.00397176, "FillType": "FILL", "OrderType": "SELL", "Uuid": "27909bd8-807b-4d6e-8553-9e05530a9bd0"}, {"Id": 48000050, "TimeStamp": "2020-01-05T01:20:24.69", "Quantity": 31.2, "Price": 0.0001273, "Total": 0.00397176, "FillType": "FILL", "OrderType": "SELL", "Uuid": "07bb31f7-534f-4008-9b43-daff79e1c0d2"}, {"Id": 48000038, "TimeStamp": "2020-01-05T01:20:15.69", "Quantity": 10.19999, "Price": 0.0001273, "Total": 0.001298458727, "FillType": "FILL", "OrderType": "SELL", "Uuid": "1f7f335c-a189-4def-bde5-e8c9cb0f1915"}, {"Id": 48000032, "TimeStamp": "2020-01-05T01:20:14.4", "Quantity": 31.2, "Price": 0.0001273, "Total": 0.00397176, "FillType": "FILL", "OrderType": "SELL", "Uuid": "7c9d6832-da20-46c6-9cf3-3253c4911818"}, {"Id": 48000022, "TimeStamp": "2020-01-05T01:20:05.38", "Quantity": 20.80092266, "Price": 0.0001273, "Total": 0.002647957454618, "FillType": "FILL", "OrderType": "SELL", "Uuid": "9d87bdf0-ffaa-488b-99fa-bad5d7a77147"}, {"Id": 48000021, "TimeStamp": "2020-01-05T01:20:05.38", "Quantity": 10.39907734, "Price": 0.00012731, "Total": 0.0013239065361554, "FillType": "FILL", "OrderType": "SELL", "Uuid": "bf3af3ce-0b9e-4c39-b438-509e181f4bf3"}, {"Id": 47998883, "TimeStamp": "2020-01-05T00:44:21.46", "Quantity": 138.35720099, "Price": 0.0001273, "Total": 0.017612871686027, "FillType": "FILL", "OrderType": "SELL", "Uuid": "98019dd1-c42e-4c5a-84a2-24ee9c353d53"}, {"Id": 47998882, "TimeStamp": "2020-01-05T00:44:21.46", "Quantity": 7.17578752, "Price": 0.00012731, "Total": 0.0009135495091712, "FillType": "FILL", "OrderType": "SELL", "Uuid": "ff6f2ed2-b5ac-4861-a082-93ed9f982971"}, {"Id": 47998881, "TimeStamp": "2020-01-05T00:44:21.46", "Quantity": 4.46701149, "Price": 0.0001275, "Total": 0.000569543964975, "FillType": "FILL", "OrderType": "SELL", "Uuid": "d012cb4f-e7c7-48a0-b2a2-8492e6a4083b"}, {"Id": 47998677, "TimeStamp": "2020-01-05T00:36:18.47", "Quantity": 4.88, "Price": 0.0001275, "Total": 0.0006222, "FillType": "FILL", "OrderType": "SELL", "Uuid": "4476753e-c982-4837-b5e7-98b91902a1f3"}, {"Id": 47998676, "TimeStamp": "2020-01-05T00:36:16.05", "Quantity": 8.27, "Price": 0.0001275, "Total": 0.001054425, "FillType": "FILL", "OrderType": "SELL", "Uuid": "6eccd516-1ca0-4123-897a-4ea4fe042a86"}, {"Id": 47998673, "TimeStamp": "2020-01-05T00:36:13.38", "Quantity": 12.23, "Price": 0.0001275, "Total": 0.001559325, "FillType": "FILL", "OrderType": "SELL", "Uuid": "135823d1-e50d-4591-b1fc-c20e10d068fb"}, {"Id": 47998671, "TimeStamp": "2020-01-05T00:36:11", "Quantity": 14.26, "Price": 0.0001275, "Total": 0.00181815, "FillType": "FILL", "OrderType": "SELL", "Uuid": "54b1d53c-f817-4592-b6eb-69a7de9ad8dd"}, {"Id": 47998669, "TimeStamp": "2020-01-05T00:36:08.44", "Quantity": 14.0, "Price": 0.0001275, "Total": 0.001785, "FillType": "FILL", "OrderType": "SELL", "Uuid": "180fc35c-ac30-48e1-ad42-3fc444bd20d9"}, {"Id": 47998666, "TimeStamp": "2020-01-05T00:35:59.02", "Quantity": 14.0, "Price": 0.0001275, "Total": 0.001785, "FillType": "FILL", "OrderType": "SELL", "Uuid": "72d70976-6c0e-4e02-b76d-15e419bae97e"}, {"Id": 47998662, "TimeStamp": "2020-01-05T00:35:50.11", "Quantity": 22.43, "Price": 0.0001275, "Total": 0.002859825, "FillType": "FILL", "OrderType": "SELL", "Uuid": "0f4c2578-06c1-4606-b35e-551db5fd9216"}, {"Id": 47998660, "TimeStamp": "2020-01-05T00:35:44.77", "Quantity": 5.46298851, "Price": 0.0001275, "Total": 0.000696531035025, "FillType": "FILL", "OrderType": "SELL", "Uuid": "d9616a8c-e22f-4d6b-bbc0-b29b233e6e5c"}, {"Id": 47998659, "TimeStamp": "2020-01-05T00:35:44.77", "Quantity": 2.96701149, "Price": 0.00012766, "Total": 0.0003787686868134, "FillType": "FILL", "OrderType": "SELL", "Uuid": "5dfe211d-c478-49b8-9c93-5020a5d9291d"}, {"Id": 47998658, "TimeStamp": "2020-01-05T00:35:39.61", "Quantity": 4.88, "Price": 0.00012766, "Total": 0.0006229808, "FillType": "FILL", "OrderType": "SELL", "Uuid": "348f5c5d-73c7-49d0-a5c6-f4f83831dba5"}, {"Id": 47998656, "TimeStamp": "2020-01-05T00:35:37.2", "Quantity": 4.88, "Price": 0.00012766, "Total": 0.0006229808, "FillType": "FILL", "OrderType": "SELL", "Uuid": "9ea5904b-1a5d-42a0-968a-4188de9c6bd1"}, {"Id": 47998655, "TimeStamp": "2020-01-05T00:35:21.55", "Quantity": 4.88, "Price": 0.00012766, "Total": 0.0006229808, "FillType": "FILL", "OrderType": "SELL", "Uuid": "c5e61986-16c3-4ae2-9db8-348d68cac0a9"}, {"Id": 47998347, "TimeStamp": "2020-01-05T00:23:36.93", "Quantity": 8.08685493, "Price": 0.0001278, "Total": 0.001033500060054, "FillType": "FILL", "OrderType": "SELL", "Uuid": "ad27a058-c11a-4540-8968-620e33503c8d"}, {"Id": 47998339, "TimeStamp": "2020-01-05T00:23:29.23", "Quantity": 7.5, "Price": 0.00012777, "Total": 0.000958275, "FillType": "FILL", "OrderType": "BUY", "Uuid": "70555151-c518-43e8-b6ef-6f0ba57906c1"}, {"Id": 47997954, "TimeStamp": "2020-01-05T00:06:04.46", "Quantity": 0.00823276, "Price": 0.00012801, "Total": 1.0538756076e-06, "FillType": "FILL", "OrderType": "SELL", "Uuid": "ea120cfe-8189-434b-9946-bd97d3ea14f7"}, {"Id": 47997953, "TimeStamp": "2020-01-05T00:06:01.86", "Quantity": 13.36580032, "Price": 0.00012801, "Total": 0.0017109560989632, "FillType": "FILL", "OrderType": "SELL", "Uuid": "4360b32f-8733-4f35-bc46-0de4b5784b6a"}, {"Id": 47997952, "TimeStamp": "2020-01-05T00:06:01.86", "Quantity": 0.00419968, "Price": 0.00012838, "Total": 5.391549184e-07, "FillType": "FILL", "OrderType": "SELL", "Uuid": "43f993de-bccb-48fb-88d7-4c7899872195"}, {"Id": 47997886, "TimeStamp": "2020-01-05T00:03:17.45", "Quantity": 103.31658, "Price": 0.00012838, "Total": 0.0132637825404, "FillType": "FILL", "OrderType": "SELL", "Uuid": "5bdbff64-23ba-4d70-a2cf-ff79fa48b3fa"}, {"Id": 47997885, "TimeStamp": "2020-01-05T00:03:16.03", "Quantity": 10.0, "Price": 0.00012838, "Total": 0.0012838, "FillType": "FILL", "OrderType": "SELL", "Uuid": "54bf9e1d-0ad6-4484-adf0-9d41c93f4875"}, {"Id": 47997577, "TimeStamp": "2020-01-05T00:00:26.44", "Quantity": 0.00270808, "Price": 0.00012888, "Total": 3.490173504e-07, "FillType": "FILL", "OrderType": "SELL", "Uuid": "0c0477a9-1e38-4b42-bcc5-d5c6fae785c2"}, {"Id": 47997569, "TimeStamp": "2020-01-05T00:00:24.84", "Quantity": 446.42313, "Price": 0.00012888, "Total": 0.0575350129944, "FillType": "FILL", "OrderType": "SELL", "Uuid": "6d271cb2-05d5-46c0-9479-bd7a39649874"}], "timestamp": 1578200649.2900386}